{"path": "/tools/amadeus/search", "url": "https://origin-daisy.onrender.com/tools/amadeus/search", "request_payload": {"originLocationCode": "ZAG", "destinationLocationCode": "MUC", "departureDate": "2025-10-24", "adults": 1, "nonStop": false, "max": 10, "travelClass": "ECONOMY", "returnDate": "2025-10-27", "currencyCode": "EUR", "includedAirlineCodes": "LH,LX,OS,SN,EW,4Y,EN"}, "status": 200, "response": {"offers": [{"id": "1", "price": "733.49", "currency": "EUR", "itineraries": [{"duration": "PT12H20M", "segments": [{"carrierCode": "OS", "number": "678", "departure": "ZAG", "departureTime": "2025-10-24T18:50:00", "arrival": "VIE", "arrivalTime": "2025-10-24T19:45:00", "aircraft": "E95"}, {"carrierCode": "LH", "number": "6321", "departure": "VIE", "departureTime": "2025-10-25T06:10:00", "arrival": "MUC", "arrivalTime": "2025-10-25T07:10:00", "aircraft": "321"}]}, {"duration": "PT13H50M", "segments": [{"carrierCode": "LH", "number": "123", "departure": "MUC", "departureTime": "2025-10-27T21:00:00", "arrival": "FRA", "arrivalTime": "2025-10-27T22:05:00", "aircraft": "321"}, {"carrierCode": "LH", "number": "6000", "departure": "FRA", "departureTime": "2025-10-28T09:30:00", "arrival": "ZAG", "arrivalTime": "2025-10-28T10:50:00", "aircraft": "223"}]}]}], "raw": {"meta": {"count": 1, "links": {"self": "https://test.api.amadeus.com/v2/shopping/flight-offers?originLocationCode=ZAG&destinationLocationCode=MUC&departureDate=2025-10-24&adults=1&returnDate=2025-10-27&currencyCode=EUR&max=10&nonStop=false&travelClass=ECONOMY&includedAirlineCodes=LH,LX,OS,SN,EW,4Y,EN"}}, "data": [{"type": "flight-offer", "id": "1", "source": "GDS", "instantTicketingRequired": false, "nonHomogeneous": false, "oneWay": false, "isUpsellOffer": false, "lastTicketingDate": "2025-10-24", "lastTicketingDateTime": "2025-10-24", "numberOfBookableSeats": 9, "itineraries": [{"duration": "PT12H20M", "segments": [{"departure": {"iataCode": "ZAG", "at": "2025-10-24T18:50:00"}, "arrival": {"iataCode": "VIE", "terminal": "3", "at": "2025-10-24T19:45:00"}, "carrierCode": "OS", "number": "678", "aircraft": {"code": "E95"}, "operating": {"carrierCode": "OS"}, "duration": "PT55M", "id": "1", "numberOfStops": 0, "blacklistedInEU": false}, {"departure": {"iataCode": "VIE", "terminal": "3", "at": "2025-10-25T06:10:00"}, "arrival": {"iataCode": "MUC", "terminal": "2", "at": "2025-10-25T07:10:00"}, "carrierCode": "LH", "number": "6321", "aircraft": {"code": "321"}, "operating": {"carrierCode": "OS"}, "duration": "PT1H", "id": "2", "numberOfStops": 0, "blacklistedInEU": false}]}, {"duration": "PT13H50M", "segments": [{"departure": {"iataCode": "MUC", "terminal": "2", "at": "2025-10-27T21:00:00"}, "arrival": {"iataCode": "FRA", "terminal": "1", "at": "2025-10-27T22:05:00"}, "carrierCode": "LH", "number": "123", "aircraft": {"code": "321"}, "operating": {"carrierCode": "LH"}, "duration": "PT1H5M", "id": "3", "numberOfStops": 0, "blacklistedInEU": false}, {"departure": {"iataCode": "FRA", "terminal": "1", "at": "2025-10-28T09:30:00"}, "arrival": {"iataCode": "ZAG", "at": "2025-10-28T10:50:00"}, "carrierCode": "LH", "number": "6000", "aircraft": {"code": "223"}, "operating": {"carrierCode": "OU"}, "duration": "PT1H20M", "id": "4", "numberOfStops": 0, "blacklistedInEU": false}]}], "price": {"currency": "EUR", "total": "733.49", "base": "425.00", "fees": [{"amount": "0.00", "type": "SUPPLIER"}, {"amount": "0.00", "type": "TICKETING"}], "grandTotal": "733.49"}, "pricingOptions": {"fareType": ["PUBLISHED"], "includedCheckedBagsOnly": true}, "validatingAirlineCodes": ["OS"], "travelerPricings": [{"travelerId": "1", "fareOption": "STANDARD", "travelerType": "ADULT", "price": {"currency": "EUR", "total": "733.49", "base": "425.00"}, "fareDetailsBySegment": [{"segmentId": "1", "cabin": "ECONOMY", "fareBasis": "WEUCLSP0", "brandedFare": "CLASSIC", "brandedFareLabel": "CLASSIC", "class": "W", "includedCheckedBags": {"quantity": 1}, "includedCabinBags": {"quantity": 1}, "amenities": [{"description": "CATERING ON EUROPE FLTS", "isChargeable": true, "amenityType": "MEAL", "amenityProvider": {"name": "BrandedFare"}}, {"description": "STANDARD SEAT RESERVATION", "isChargeable": false, "amenityType": "BRANDED_FARES", "amenityProvider": {"name": "BrandedFare"}}, {"description": "MILEAGE ACCRUAL", "isChargeable": false, "amenityType": "BRANDED_FARES", "amenityProvider": {"name": "BrandedFare"}}, {"description": "UPGRADE ELIGIBILITY", "isChargeable": true, "amenityType": "BRANDED_FARES", "amenityProvider": {"name": "BrandedFare"}}, {"description": "PREFERRED SEAT RESERVATION", "isChargeable": true, "amenityType": "BRANDED_FARES", "amenityProvider": {"name": "BrandedFare"}}, {"description": "CHANGE BEFORE DEPARTURE", "isChargeable": true, "amenityType": "BRANDED_FARES", "amenityProvider": {"name": "BrandedFare"}}, {"description": "CHANGE AFTER DEPARTURE", "isChargeable": true, "amenityType": "BRANDED_FARES", "amenityProvider": {"name": "BrandedFare"}}]}, {"segmentId": "2", "cabin": "ECONOMY", "fareBasis": "QEUCLST0", "class": "Q", "includedCheckedBags": {"quantity": 1}, "includedCabinBags": {"quantity": 1}}, {"segmentId": "3", "cabin": "ECONOMY", "fareBasis": "QEUCLST0", "brandedFare": "CLASSIC", "brandedFareLabel": "CLASSIC", "class": "Q", "includedCheckedBags": {"quantity": 1}, "includedCabinBags": {"quantity": 1}, "amenities": [{"description": "CATERING ON EUROPE FLTS", "isChargeable": true, "amenityType": "MEAL", "amenityProvider": {"name": "BrandedFare"}}, {"description": "STANDARD SEAT RESERVATION", "isChargeable": false, "amenityType": "BRANDED_FARES", "amenityProvider": {"name": "BrandedFare"}}, {"description": "MILEAGE ACCRUAL", "isChargeable": false, "amenityType": "BRANDED_FARES", "amenityProvider": {"name": "BrandedFare"}}, {"description": "UPGRADE ELIGIBILITY", "isChargeable": true, "amenityType": "BRANDED_FARES", "amenityProvider": {"name": "BrandedFare"}}, {"description": "PREFERRED SEAT RESERVATION", "isChargeable": true, "amenityType": "BRANDED_FARES", "amenityProvider": {"name": "BrandedFare"}}, {"description": "CHANGE BEFORE DEPARTURE", "isChargeable": true, "amenityType": "BRANDED_FARES", "amenityProvider": {"name": "BrandedFare"}}, {"description": "CHANGE AFTER DEPARTURE", "isChargeable": true, "amenityType": "BRANDED_FARES", "amenityProvider": {"name": "BrandedFare"}}]}, {"segmentId": "4", "cabin": "ECONOMY", "fareBasis": "QEUCLST0", "brandedFare": "CLASSIC", "brandedFareLabel": "CLASSIC", "class": "Q", "includedCheckedBags": {"quantity": 1}, "includedCabinBags": {"quantity": 1}, "amenities": [{"description": "CATERING ON EUROPE FLTS", "isChargeable": true, "amenityType": "MEAL", "amenityProvider": {"name": "BrandedFare"}}, {"description": "STANDARD SEAT RESERVATION", "isChargeable": false, "amenityType": "BRANDED_FARES", "amenityProvider": {"name": "BrandedFare"}}, {"description": "MILEAGE ACCRUAL", "isChargeable": false, "amenityType": "BRANDED_FARES", "amenityProvider": {"name": "BrandedFare"}}, {"description": "UPGRADE ELIGIBILITY", "isChargeable": true, "amenityType": "BRANDED_FARES", "amenityProvider": {"name": "BrandedFare"}}, {"description": "PREFERRED SEAT RESERVATION", "isChargeable": true, "amenityType": "BRANDED_FARES", "amenityProvider": {"name": "BrandedFare"}}, {"description": "CHANGE BEFORE DEPARTURE", "isChargeable": true, "amenityType": "BRANDED_FARES", "amenityProvider": {"name": "BrandedFare"}}, {"description": "CHANGE AFTER DEPARTURE", "isChargeable": true, "amenityType": "BRANDED_FARES", "amenityProvider": {"name": "BrandedFare"}}]}]}]}], "dictionaries": {"locations": {"ZAG": {"cityCode": "ZAG", "countryCode": "HR"}, "VIE": {"cityCode": "VIE", "countryCode": "AT"}, "FRA": {"cityCode": "FRA", "countryCode": "DE"}, "MUC": {"cityCode": "MUC", "countryCode": "DE"}}, "aircraft": {"223": "AIRBUS  A220-300", "321": "AIRBUS A321", "E95": "EMBRAER 195"}, "currencies": {"EUR": "EURO"}, "carriers": {"OS": "AUSTRIAN AIRLINES", "OU": "CROATIA AIRLINES", "LH": "LUFTHANSA"}}}}}